{"nm":"c1","ddd":0,"h":1080,"w":1080,"meta":{"g":"@lottiefiles/toolkit-js 0.26.1"},"layers":[{"ty":4,"nm":"Layer 1/c[1-2] Outlines","sr":1,"st":0,"op":150.000006109625,"ip":0,"hd":false,"ddd":0,"bm":0,"hasMask":false,"ao":0,"ks":{"a":{"a":0,"k":[544.585,972.955,0],"ix":1},"s":{"a":0,"k":[100,100,100],"ix":6},"sk":{"a":0,"k":0},"p":{"a":0,"k":[544.585,1012.955,0],"ix":2},"r":{"a":0,"k":0,"ix":10},"sa":{"a":0,"k":0},"o":{"a":0,"k":100,"ix":11}},"ef":[],"shapes":[{"ty":"gr","bm":0,"hd":false,"mn":"ADBE Vector Group","nm":"Group 1","ix":2,"cix":2,"np":4,"it":[{"ty":"sh","bm":0,"hd":false,"mn":"ADBE Vector Shape - Group","nm":"Path 1","ix":1,"d":1,"ks":{"a":0,"k":{"c":true,"i":[[0,-43.113],[43.113,0],[0,43.113],[-43.113,0]],"o":[[0,43.113],[-43.113,0],[0,-43.113],[43.113,0]],"v":[[78.063,21.832],[0,99.895],[-78.063,21.832],[0,-56.231]]},"ix":2}},{"ty":"fl","bm":0,"hd":false,"mn":"ADBE Vector Graphic - Fill","nm":"Fill 1","c":{"a":0,"k":[0.0588,0.3216,0.3843],"ix":4},"r":1,"o":{"a":0,"k":100,"ix":5}},{"ty":"tr","a":{"a":0,"k":[0,0],"ix":1},"s":{"a":1,"k":[{"o":{"x":0.167,"y":0.167},"i":{"x":0.833,"y":0.833},"s":[100,100],"t":14},{"o":{"x":0.167,"y":0.167},"i":{"x":0.833,"y":0.833},"s":[130,130],"t":29},{"s":[100,100],"t":44.0000017921567}],"ix":3},"sk":{"a":0,"k":0,"ix":4},"p":{"a":0,"k":[104.245,1057.769],"ix":2},"r":{"a":0,"k":0,"ix":6},"sa":{"a":0,"k":0,"ix":5},"o":{"a":0,"k":100,"ix":7}}]},{"ty":"gr","bm":0,"hd":false,"mn":"ADBE Vector Group","nm":"Group 2","ix":3,"cix":2,"np":4,"it":[{"ty":"sh","bm":0,"hd":false,"mn":"ADBE Vector Shape - Group","nm":"Path 1","ix":1,"d":1,"ks":{"a":0,"k":{"c":true,"i":[[0,-43.112],[43.113,0],[0,43.113],[-43.113,0]],"o":[[0,43.113],[-43.113,0],[0,-43.112],[43.113,0]],"v":[[78.063,10.573],[0,88.636],[-78.063,10.573],[0,-67.49]]},"ix":2}},{"ty":"fl","bm":0,"hd":false,"mn":"ADBE Vector Graphic - Fill","nm":"Fill 1","c":{"a":0,"k":[0.0588,0.3216,0.3843],"ix":4},"r":1,"o":{"a":0,"k":100,"ix":5}},{"ty":"tr","a":{"a":0,"k":[0,0],"ix":1},"s":{"a":1,"k":[{"o":{"x":0.167,"y":0.167},"i":{"x":0.833,"y":0.833},"s":[100,100],"t":16},{"o":{"x":0.167,"y":0.167},"i":{"x":0.833,"y":0.833},"s":[165,165],"t":31},{"s":[100,100],"t":46.0000018736184}],"ix":3},"sk":{"a":0,"k":0,"ix":4},"p":{"a":0,"k":[219.342,1028.51],"ix":2},"r":{"a":0,"k":0,"ix":6},"sa":{"a":0,"k":0,"ix":5},"o":{"a":0,"k":100,"ix":7}}]},{"ty":"gr","bm":0,"hd":false,"mn":"ADBE Vector Group","nm":"Group 3","ix":4,"cix":2,"np":4,"it":[{"ty":"sh","bm":0,"hd":false,"mn":"ADBE Vector Shape - Group","nm":"Path 1","ix":1,"d":1,"ks":{"a":0,"k":{"c":true,"i":[[0,-43.113],[43.113,0],[0,43.113],[-43.113,0]],"o":[[0,43.113],[-43.113,0],[0,-43.113],[43.113,0]],"v":[[78.063,16.464],[0,94.527],[-78.063,16.464],[0,-61.599]]},"ix":2}},{"ty":"fl","bm":0,"hd":false,"mn":"ADBE Vector Graphic - Fill","nm":"Fill 1","c":{"a":0,"k":[0.0588,0.3216,0.3843],"ix":4},"r":1,"o":{"a":0,"k":100,"ix":5}},{"ty":"tr","a":{"a":0,"k":[0,0],"ix":1},"s":{"a":1,"k":[{"o":{"x":0.167,"y":0.167},"i":{"x":0.833,"y":0.833},"s":[100,100],"t":18},{"o":{"x":0.167,"y":0.167},"i":{"x":0.833,"y":0.833},"s":[130,130],"t":33},{"s":[100,100],"t":48.0000019550801}],"ix":3},"sk":{"a":0,"k":0,"ix":4},"p":{"a":0,"k":[324.771,994.401],"ix":2},"r":{"a":0,"k":0,"ix":6},"sa":{"a":0,"k":0,"ix":5},"o":{"a":0,"k":100,"ix":7}}]},{"ty":"gr","bm":0,"hd":false,"mn":"ADBE Vector Group","nm":"Group 4","ix":5,"cix":2,"np":2,"it":[{"ty":"sh","bm":0,"hd":false,"mn":"ADBE Vector Shape - Group","nm":"Path 1","ix":1,"d":1,"ks":{"a":0,"k":{"c":true,"i":[[0,-43.113],[43.113,0],[0,43.112],[-43.113,0]],"o":[[0,43.112],[-43.113,0],[0,-43.113],[43.113,0]],"v":[[78.063,0],[0,78.063],[-78.063,0],[0,-78.063]]},"ix":2}},{"ty":"fl","bm":0,"hd":false,"mn":"ADBE Vector Graphic - Fill","nm":"Fill 1","c":{"a":0,"k":[0.0588,0.3216,0.3843],"ix":4},"r":1,"o":{"a":0,"k":100,"ix":5}},{"ty":"tr","a":{"a":0,"k":[0,0],"ix":1},"s":{"a":1,"k":[{"o":{"x":0.167,"y":0.167},"i":{"x":0.833,"y":0.833},"s":[100,100],"t":20},{"o":{"x":0.167,"y":0.167},"i":{"x":0.833,"y":0.833},"s":[130,130],"t":35},{"s":[100,100],"t":50.0000020365418}],"ix":3},"sk":{"a":0,"k":0,"ix":4},"p":{"a":0,"k":[407.813,995.563],"ix":2},"r":{"a":0,"k":0,"ix":6},"sa":{"a":0,"k":0,"ix":5},"o":{"a":0,"k":100,"ix":7}}]},{"ty":"gr","bm":0,"hd":false,"mn":"ADBE Vector Group","nm":"Group 5","ix":6,"cix":2,"np":4,"it":[{"ty":"sh","bm":0,"hd":false,"mn":"ADBE Vector Shape - Group","nm":"Path 1","ix":1,"d":1,"ks":{"a":0,"k":{"c":true,"i":[[0,-43.113],[43.114,0],[0,43.113],[-43.113,0]],"o":[[0,43.113],[-43.113,0],[0,-43.113],[43.114,0]],"v":[[78.063,21.832],[0,99.895],[-78.063,21.832],[0,-56.231]]},"ix":2}},{"ty":"fl","bm":0,"hd":false,"mn":"ADBE Vector Graphic - Fill","nm":"Fill 1","c":{"a":0,"k":[0.0588,0.3216,0.3843],"ix":4},"r":1,"o":{"a":0,"k":100,"ix":5}},{"ty":"tr","a":{"a":0,"k":[0,0],"ix":1},"s":{"a":1,"k":[{"o":{"x":0.167,"y":0.167},"i":{"x":0.833,"y":0.833},"s":[100,100],"t":22},{"o":{"x":0.167,"y":0.167},"i":{"x":0.833,"y":0.833},"s":[130,130],"t":37},{"s":[100,100],"t":52.0000021180034}],"ix":3},"sk":{"a":0,"k":0,"ix":4},"p":{"a":0,"k":[984.925,1057.769],"ix":2},"r":{"a":0,"k":0,"ix":6},"sa":{"a":0,"k":0,"ix":5},"o":{"a":0,"k":100,"ix":7}}]},{"ty":"gr","bm":0,"hd":false,"mn":"ADBE Vector Group","nm":"Group 6","ix":7,"cix":2,"np":4,"it":[{"ty":"sh","bm":0,"hd":false,"mn":"ADBE Vector Shape - Group","nm":"Path 1","ix":1,"d":1,"ks":{"a":0,"k":{"c":true,"i":[[0,-43.113],[43.113,0],[0,43.113],[-43.113,0]],"o":[[0,43.113],[-43.113,0],[0,-43.113],[43.113,0]],"v":[[78.063,25.168],[0,103.231],[-78.063,25.168],[0,-52.895]]},"ix":2}},{"ty":"fl","bm":0,"hd":false,"mn":"ADBE Vector Graphic - Fill","nm":"Fill 1","c":{"a":0,"k":[0.0588,0.3216,0.3843],"ix":4},"r":1,"o":{"a":0,"k":100,"ix":5}},{"ty":"tr","a":{"a":0,"k":[0,0],"ix":1},"s":{"a":1,"k":[{"o":{"x":0.167,"y":0.167},"i":{"x":0.833,"y":0.833},"s":[100,100],"t":24},{"o":{"x":0.167,"y":0.167},"i":{"x":0.833,"y":0.833},"s":[130,130],"t":39},{"s":[100,100],"t":54.0000021994651}],"ix":3},"sk":{"a":0,"k":0,"ix":4},"p":{"a":0,"k":[894.84,1031.105],"ix":2},"r":{"a":0,"k":0,"ix":6},"sa":{"a":0,"k":0,"ix":5},"o":{"a":0,"k":100,"ix":7}}]},{"ty":"gr","bm":0,"hd":false,"mn":"ADBE Vector Group","nm":"Group 7","ix":8,"cix":2,"np":4,"it":[{"ty":"sh","bm":0,"hd":false,"mn":"ADBE Vector Shape - Group","nm":"Path 1","ix":1,"d":1,"ks":{"a":0,"k":{"c":true,"i":[[0,-43.112],[43.113,0],[0,43.113],[-43.113,0]],"o":[[0,43.113],[-43.113,0],[0,-43.112],[43.113,0]],"v":[[78.063,10.573],[0,88.636],[-78.063,10.573],[0,-67.49]]},"ix":2}},{"ty":"fl","bm":0,"hd":false,"mn":"ADBE Vector Graphic - Fill","nm":"Fill 1","c":{"a":0,"k":[0.0588,0.3216,0.3843],"ix":4},"r":1,"o":{"a":0,"k":100,"ix":5}},{"ty":"tr","a":{"a":0,"k":[0,0],"ix":1},"s":{"a":1,"k":[{"o":{"x":0.167,"y":0.167},"i":{"x":0.833,"y":0.833},"s":[100,100],"t":26},{"o":{"x":0.167,"y":0.167},"i":{"x":0.833,"y":0.833},"s":[143,143],"t":41},{"s":[100,100],"t":56.0000022809268}],"ix":3},"sk":{"a":0,"k":0,"ix":4},"p":{"a":0,"k":[783.937,1012.51],"ix":2},"r":{"a":0,"k":0,"ix":6},"sa":{"a":0,"k":0,"ix":5},"o":{"a":0,"k":100,"ix":7}}]},{"ty":"gr","bm":0,"hd":false,"mn":"ADBE Vector Group","nm":"Group 8","ix":10,"cix":2,"np":4,"it":[{"ty":"sh","bm":0,"hd":false,"mn":"ADBE Vector Shape - Group","nm":"Path 1","ix":1,"d":1,"ks":{"a":0,"k":{"c":true,"i":[[0,-43.112],[43.113,0],[0,43.113],[-43.113,0]],"o":[[0,43.113],[-43.113,0],[0,-43.112],[43.113,0]],"v":[[78.063,10.573],[0,88.636],[-78.063,10.573],[0,-67.49]]},"ix":2}},{"ty":"fl","bm":0,"hd":false,"mn":"ADBE Vector Graphic - Fill","nm":"Fill 1","c":{"a":0,"k":[0.0588,0.3216,0.3843],"ix":4},"r":1,"o":{"a":0,"k":100,"ix":5}},{"ty":"tr","a":{"a":0,"k":[0,0],"ix":1},"s":{"a":1,"k":[{"o":{"x":0.167,"y":0.167},"i":{"x":0.833,"y":0.833},"s":[100,100],"t":28},{"o":{"x":0.167,"y":0.167},"i":{"x":0.833,"y":0.833},"s":[130,130],"t":43},{"s":[100,100],"t":58.0000023623884}],"ix":3},"sk":{"a":0,"k":0,"ix":4},"p":{"a":0,"k":[676.354,990.51],"ix":2},"r":{"a":0,"k":0,"ix":6},"sa":{"a":0,"k":0,"ix":5},"o":{"a":0,"k":100,"ix":7}}]},{"ty":"gr","bm":0,"hd":false,"mn":"ADBE Vector Group","nm":"Group 9","ix":11,"cix":2,"np":3,"it":[{"ty":"sh","bm":0,"hd":false,"mn":"ADBE Vector Shape - Group","nm":"Path 1","ix":1,"d":1,"ks":{"a":1,"k":[{"o":{"x":0.167,"y":0.167},"i":{"x":0.833,"y":0.833},"s":[{"c":true,"i":[[-2.7,-83.058],[68.964,0],[0.797,68.959],[-57.042,4.34],[-5.945,-73.071],[-19.163,28.407]],"o":[[2.241,68.928],[-68.964,0],[-0.96,-83.058],[0.958,5.09],[0,0],[65.087,8.407]],"v":[[124.87,15.103],[0,139.973],[-124.87,15.103],[-17.788,-107.295],[5.615,-10.634],[29.083,-106.362]]}],"t":0},{"o":{"x":0.167,"y":0.167},"i":{"x":0.833,"y":0.833},"s":[{"c":true,"i":[[0,-62.296],[68.964,0],[0,68.964],[-79.542,7.34],[-3.945,-40.321],[-7.913,29.907]],"o":[[0,68.964],[-68.964,0],[0,-60.002],[0.958,5.09],[0,0],[63.087,0.407]],"v":[[124.87,15.103],[0,139.973],[-124.87,15.103],[-5.788,-108.795],[6.115,-47.134],[17.083,-107.862]]}],"t":5},{"o":{"x":0.167,"y":0.167},"i":{"x":0.667,"y":1},"s":[{"c":true,"i":[[0,-62.296],[68.964,0],[0,68.964],[-97.042,3.84],[-1.445,-25.821],[-2.413,8.407]],"o":[[0,68.964],[-68.964,0],[0,-60.002],[0.958,5.09],[0,0],[75.087,0.907]],"v":[[124.87,15.103],[0,139.973],[-124.87,15.103],[1.712,-110.795],[5.615,-78.134],[10.583,-110.862]]}],"t":10},{"o":{"x":0.333,"y":0},"i":{"x":0.667,"y":1},"s":[{"c":true,"i":[[0,-62.296],[68.964,0],[0,68.964],[-97.042,3.84],[-1.469,0.011],[-0.163,-0.093]],"o":[[0,68.964],[-68.964,0],[0,-60.002],[-0.042,-0.285],[1.491,-0.011],[75.087,0.907]],"v":[[124.87,15.103],[0,139.973],[-124.87,15.103],[1.712,-110.795],[6.24,-111.009],[10.583,-110.862]]}],"t":15},{"o":{"x":0.12,"y":0},"i":{"x":0,"y":1},"s":[{"c":true,"i":[[0,-62.296],[68.964,0],[0,68.964],[-57.917,9.261],[-26.07,0.304],[-0.163,-0.093]],"o":[[0,68.964],[-68.964,0],[0,-60.002],[-0.042,-0.285],[19.615,-0.229],[62.524,10.345]],"v":[[124.87,15.103],[0,139.973],[-124.87,15.103],[-33.913,-110.715],[6.24,-137.259],[40.645,-112.8]]}],"t":20},{"s":[{"c":true,"i":[[0,-62.296],[68.964,0],[0,68.964],[-74.884,5.124],[-1.469,0.011],[-0.163,-0.093]],"o":[[0,68.964],[-68.964,0],[0,-60.002],[-0.042,-0.285],[1.491,-0.011],[75.087,0.907]],"v":[[124.87,15.103],[0,139.973],[-124.87,15.103],[1.712,-110.795],[6.24,-111.009],[10.583,-110.862]]}],"t":30.0000012219251}],"ix":2}},{"ty":"mm","bm":0,"hd":false,"mn":"ADBE Vector Filter - Merge","nm":"Merge Paths 1","mm":4},{"ty":"fl","bm":0,"hd":false,"mn":"ADBE Vector Graphic - Fill","nm":"Fill 1","c":{"a":0,"k":[0.0588,0.3216,0.3843],"ix":4},"r":1,"o":{"a":0,"k":100,"ix":5}},{"ty":"tr","a":{"a":0,"k":[0,0],"ix":1},"s":{"a":1,"k":[{"o":{"x":0.167,"y":0.167},"i":{"x":0.833,"y":0.833},"s":[100,100],"t":30},{"o":{"x":0.167,"y":0.167},"i":{"x":0.833,"y":0.833},"s":[110,110],"t":50},{"s":[100,100],"t":70.0000028511585}],"ix":3},"sk":{"a":0,"k":0,"ix":4},"p":{"a":0,"k":[548.83,972.955],"ix":2},"r":{"a":0,"k":0,"ix":6},"sa":{"a":0,"k":0,"ix":5},"o":{"a":0,"k":100,"ix":7}}]}],"ind":1},{"ty":0,"nm":"Pre-comp 1","sr":1,"st":0,"op":150.000006109625,"ip":0,"hd":false,"ddd":0,"bm":0,"hasMask":false,"ao":0,"ks":{"a":{"a":0,"k":[552,550,0],"ix":1},"s":{"a":0,"k":[100,100,100],"ix":6},"sk":{"a":0,"k":0},"p":{"a":1,"k":[{"o":{"x":0.167,"y":0.167},"i":{"x":0.667,"y":1},"s":[552,708,0],"t":0,"ti":[0,23.333,0],"to":[0,-30,0]},{"o":{"x":0.333,"y":0},"i":{"x":0.667,"y":1},"s":[552,528,0],"t":28,"ti":[0,0,0],"to":[0,-23.333,0]},{"o":{"x":0.333,"y":0},"i":{"x":0.667,"y":1},"s":[552,568,0],"t":51,"ti":[0,0,0],"to":[0,0,0]},{"o":{"x":0.333,"y":0},"i":{"x":0.667,"y":1},"s":[552,528,0],"t":73.999,"ti":[0,0,0],"to":[0,0,0]},{"o":{"x":0.333,"y":0},"i":{"x":0.667,"y":1},"s":[552,568,0],"t":97,"ti":[0,6.667,0],"to":[0,0,0]},{"s":[552,528,0],"t":120.0000048877}],"ix":2},"r":{"a":0,"k":0,"ix":10},"sa":{"a":0,"k":0},"o":{"a":0,"k":100,"ix":11}},"ef":[],"w":1080,"h":1080,"refId":"comp_0","ind":2}],"v":"5.7.3","fr":29.9700012207031,"op":120.0000048877,"ip":0,"assets":[{"nm":"","id":"comp_0","layers":[{"ty":4,"nm":"Layer 3/c[1-2] Outlines","sr":1,"st":0,"op":150.000006109625,"ip":0,"hd":false,"ddd":0,"bm":0,"hasMask":false,"ao":0,"ks":{"a":{"a":0,"k":[554.691,496.304,0],"ix":1},"s":{"a":0,"k":[100,100,100],"ix":6},"sk":{"a":0,"k":0},"p":{"a":0,"k":[554.691,496.304,0],"ix":2},"r":{"a":0,"k":0,"ix":10},"sa":{"a":0,"k":0},"o":{"a":0,"k":100,"ix":11}},"ef":[],"shapes":[{"ty":"gr","bm":0,"hd":false,"mn":"ADBE Vector Group","nm":"Group 1","ix":1,"cix":2,"np":2,"it":[{"ty":"sh","bm":0,"hd":false,"mn":"ADBE Vector Shape - Group","nm":"Path 1","ix":1,"d":1,"ks":{"a":0,"k":{"c":true,"i":[[0,0],[8.992,7.74],[0,0],[0.362,-7.095]],"o":[[0,0],[0,0],[2.869,0.565],[0,0]],"v":[[4.758,13.171],[-8.13,-9.941],[-5.236,-13.171],[7.768,12.603]]},"ix":2}},{"ty":"fl","bm":0,"hd":false,"mn":"ADBE Vector Graphic - Fill","nm":"Fill 1","c":{"a":0,"k":[0.9882,0.9961,1],"ix":4},"r":1,"o":{"a":0,"k":100,"ix":5}},{"ty":"tr","a":{"a":0,"k":[0,0],"ix":1},"s":{"a":0,"k":[100,100],"ix":3},"sk":{"a":0,"k":0,"ix":4},"p":{"a":0,"k":[600.243,399.1],"ix":2},"r":{"a":0,"k":0,"ix":6},"sa":{"a":0,"k":0,"ix":5},"o":{"a":0,"k":100,"ix":7}}]},{"ty":"gr","bm":0,"hd":false,"mn":"ADBE Vector Group","nm":"Group 2","ix":2,"cix":2,"np":2,"it":[{"ty":"sh","bm":0,"hd":false,"mn":"ADBE Vector Shape - Group","nm":"Path 1","ix":1,"d":1,"ks":{"a":0,"k":{"c":true,"i":[[0.727,1.723],[0,0],[0.524,-2.317]],"o":[[0,0],[0.217,1.644],[-0.096,-2.38]],"v":[[-1.003,-3.171],[0.786,-3.02],[0.05,3.171]]},"ix":2}},{"ty":"fl","bm":0,"hd":false,"mn":"ADBE Vector Graphic - Fill","nm":"Fill 1","c":{"a":0,"k":[0.9882,0.9961,1],"ix":4},"r":1,"o":{"a":0,"k":100,"ix":5}},{"ty":"tr","a":{"a":0,"k":[0,0],"ix":1},"s":{"a":0,"k":[100,100],"ix":3},"sk":{"a":0,"k":0,"ix":4},"p":{"a":0,"k":[609.376,428.694],"ix":2},"r":{"a":0,"k":0,"ix":6},"sa":{"a":0,"k":0,"ix":5},"o":{"a":0,"k":100,"ix":7}}]},{"ty":"gr","bm":0,"hd":false,"mn":"ADBE Vector Group","nm":"Group 3","ix":3,"cix":2,"np":2,"it":[{"ty":"sh","bm":0,"hd":false,"mn":"ADBE Vector Shape - Group","nm":"Path 1","ix":1,"d":1,"ks":{"a":0,"k":{"c":true,"i":[[1.021,2.15],[0,0],[0.054,-2.715],[0,0]],"o":[[0,0],[0.67,2.503],[0,0],[-0.361,-2.483]],"v":[[-1.888,-2.926],[0.849,-4.047],[1.834,3.761],[0.138,4.047]]},"ix":2}},{"ty":"fl","bm":0,"hd":false,"mn":"ADBE Vector Graphic - Fill","nm":"Fill 1","c":{"a":0,"k":[0.9882,0.9961,1],"ix":4},"r":1,"o":{"a":0,"k":100,"ix":5}},{"ty":"tr","a":{"a":0,"k":[0,0],"ix":1},"s":{"a":0,"k":[100,100],"ix":3},"sk":{"a":0,"k":0,"ix":4},"p":{"a":0,"k":[608.089,419.369],"ix":2},"r":{"a":0,"k":0,"ix":6},"sa":{"a":0,"k":0,"ix":5},"o":{"a":0,"k":100,"ix":7}}]},{"ty":"gr","bm":0,"hd":false,"mn":"ADBE Vector Group","nm":"Group 4","ix":4,"cix":2,"np":2,"it":[{"ty":"sh","bm":0,"hd":false,"mn":"ADBE Vector Shape - Group","nm":"Path 1","ix":1,"d":1,"ks":{"a":0,"k":{"c":true,"i":[[-8.923,-38.935],[0,0],[-42.585,8.517],[-0.811,4.866],[-12.167,10.139],[0,0],[27.579,30.418],[-10.14,-5.273],[38.922,-25.634]],"o":[[0,0],[0,0],[0,0],[0,0],[0,0],[0,0],[0,0],[0,0],[0,0]],"v":[[-50.493,36.949],[-42.788,28.026],[19.67,43.438],[3.853,30.866],[37.11,24.782],[26.971,22.348],[31.837,-25.915],[51.711,-25.915],[-24.132,-26.321]]},"ix":2}},{"ty":"fl","bm":0,"hd":false,"mn":"ADBE Vector Graphic - Fill","nm":"Fill 1","c":{"a":0,"k":[1,1,1],"ix":4},"r":1,"o":{"a":0,"k":100,"ix":5}},{"ty":"tr","a":{"a":0,"k":[0,0],"ix":1},"s":{"a":0,"k":[100,100],"ix":3},"sk":{"a":0,"k":0,"ix":4},"p":{"a":0,"k":[539.901,405.066],"ix":2},"r":{"a":0,"k":0,"ix":6},"sa":{"a":0,"k":0,"ix":5},"o":{"a":0,"k":100,"ix":7}}]},{"ty":"gr","bm":0,"hd":false,"mn":"ADBE Vector Group","nm":"Group 6","ix":5,"cix":2,"np":2,"it":[{"ty":"sh","bm":0,"hd":false,"mn":"ADBE Vector Shape - Group","nm":"Path 1","ix":1,"d":1,"ks":{"a":0,"k":{"c":true,"i":[[1.471,0],[0,0],[0.82,1.093],[0,1.013],[0,0],[0,0],[0,0],[0.564,-0.751]],"o":[[0,0],[-1.471,0],[-0.565,-0.751],[0,0],[0,0],[0,0],[0,1.013],[-0.822,1.093]],"v":[[36.174,11.995],[-36.172,11.995],[-39.77,10.195],[-40.67,7.497],[-40.67,-11.994],[40.671,-11.994],[40.671,7.497],[39.773,10.195]]},"ix":2}},{"ty":"fl","bm":0,"hd":false,"mn":"ADBE Vector Graphic - Fill","nm":"Fill 1","c":{"a":0,"k":[0.4353,0.4353,0.4353],"ix":4},"r":1,"o":{"a":0,"k":100,"ix":5}},{"ty":"tr","a":{"a":0,"k":[0,0],"ix":1},"s":{"a":0,"k":[100,100],"ix":3},"sk":{"a":0,"k":0,"ix":4},"p":{"a":0,"k":[554.327,588.686],"ix":2},"r":{"a":0,"k":0,"ix":6},"sa":{"a":0,"k":0,"ix":5},"o":{"a":0,"k":100,"ix":7}}]},{"ty":"gr","bm":0,"hd":false,"mn":"ADBE Vector Group","nm":"Group 7","ix":6,"cix":2,"np":2,"it":[{"ty":"sh","bm":0,"hd":false,"mn":"ADBE Vector Shape - Group","nm":"Path 1","ix":1,"d":1,"ks":{"a":0,"k":{"c":true,"i":[[0.931,0],[0,0],[0.634,0.503],[0,1.183],[0,0],[-0.658,0.671],[-1.043,0],[0,0],[-0.668,-0.639],[0,-1.057],[0,0],[0.789,-0.683]],"o":[[0,0],[-0.873,0],[-0.861,-0.681],[0,0],[0,-1.013],[0.675,-0.691],[0,0],[0.999,0],[0.708,0.678],[0,0],[0,1.125],[-0.653,0.564]],"v":[[46.202,11.995],[-46.203,11.995],[-48.513,11.192],[-49.925,8.273],[-49.925,-8.272],[-48.863,-10.875],[-46.203,-11.994],[46.202,-11.994],[48.775,-10.962],[49.925,-8.272],[49.925,8.273],[48.637,11.09]]},"ix":2}},{"ty":"fl","bm":0,"hd":false,"mn":"ADBE Vector Graphic - Fill","nm":"Fill 1","c":{"a":0,"k":[0,0,0],"ix":4},"r":1,"o":{"a":0,"k":100,"ix":5}},{"ty":"tr","a":{"a":0,"k":[0,0],"ix":1},"s":{"a":0,"k":[100,100],"ix":3},"sk":{"a":0,"k":0,"ix":4},"p":{"a":0,"k":[554.328,564.932],"ix":2},"r":{"a":0,"k":0,"ix":6},"sa":{"a":0,"k":0,"ix":5},"o":{"a":0,"k":100,"ix":7}}]},{"ty":"gr","bm":0,"hd":false,"mn":"ADBE Vector Group","nm":"Group 8","ix":7,"cix":2,"np":3,"it":[{"ty":"sh","bm":0,"hd":false,"mn":"ADBE Vector Shape - Group","nm":"Path 1","ix":1,"d":1,"ks":{"a":0,"k":{"c":true,"i":[[0,34.867],[50.821,0],[0,-50.82],[-28.588,-15.611],[0,0],[0,0],[0,0]],"o":[[0,-50.82],[-50.819,0],[0,34.867],[0,0],[0,0],[0,0],[28.587,-15.611]],"v":[[92.018,-7.599],[0,-99.616],[-92.017,-7.599],[-44.033,73.213],[-44.033,99.616],[44.034,99.616],[44.034,73.213]]},"ix":2}},{"ty":"gf","bm":0,"hd":false,"mn":"ADBE Vector Graphic - G-Fill","nm":"Gradient Fill 1","e":{"a":0,"k":[40,96],"ix":6},"g":{"p":3,"k":{"a":0,"k":[0,1,0.9058823529411765,0.17647058823529413,0.5,1,0.9058823529411765,0.17647058823529413,1,1,0.6588235294117647,0.16470588235294117],"ix":9}},"t":1,"a":{"a":0,"k":0},"h":{"a":0,"k":0},"s":{"a":0,"k":[-41,-91],"ix":5},"r":1,"o":{"a":0,"k":100,"ix":10}},{"ty":"fl","bm":0,"hd":false,"mn":"ADBE Vector Graphic - Fill","nm":"Fill 1","c":{"a":0,"k":[0.1412,0.502,0.2392],"ix":4},"r":1,"o":{"a":0,"k":100,"ix":5}},{"ty":"tr","a":{"a":0,"k":[0,0],"ix":1},"s":{"a":0,"k":[100,100],"ix":3},"sk":{"a":0,"k":0,"ix":4},"p":{"a":0,"k":[554.691,456.54],"ix":2},"r":{"a":0,"k":0,"ix":6},"sa":{"a":0,"k":0,"ix":5},"o":{"a":0,"k":100,"ix":7}}]},{"ty":"gr","bm":0,"hd":false,"mn":"ADBE Vector Group","nm":"Group 9","ix":8,"cix":2,"np":2,"it":[{"ty":"sh","bm":0,"hd":false,"mn":"ADBE Vector Shape - Group","nm":"Path 1","ix":1,"d":1,"ks":{"a":0,"k":{"c":true,"i":[[0,0],[0,0],[-1.057,-1.872],[0,-3.306],[0,0],[0,0],[0,0]],"o":[[0,0],[1.66,1.439],[1.59,2.817],[0,0],[0,0],[0,0],[0,0]],"v":[[-3.636,-31.53],[8.73,-20.81],[12.826,-15.801],[15.277,-6.47],[15.277,31.53],[-15.278,9.515],[-14.875,-26.362]]},"ix":2}},{"ty":"fl","bm":0,"hd":false,"mn":"ADBE Vector Graphic - Fill","nm":"Fill 1","c":{"a":0,"k":[0.5451,0.5451,0.5451],"ix":4},"r":1,"o":{"a":0,"k":100,"ix":5}},{"ty":"tr","a":{"a":0,"k":[0,0],"ix":1},"s":{"a":0,"k":[100,100],"ix":3},"sk":{"a":0,"k":0,"ix":4},"p":{"a":0,"k":[604.024,588.807],"ix":2},"r":{"a":0,"k":0,"ix":6},"sa":{"a":0,"k":0,"ix":5},"o":{"a":0,"k":100,"ix":7}}]},{"ty":"gr","bm":0,"hd":false,"mn":"ADBE Vector Group","nm":"Group 10","ix":9,"cix":2,"np":2,"it":[{"ty":"sh","bm":0,"hd":false,"mn":"ADBE Vector Shape - Group","nm":"Path 1","ix":1,"d":1,"ks":{"a":0,"k":{"c":true,"i":[[0,0],[0,0],[1.056,-1.872],[0,-3.306],[0,0],[0,0],[0,0]],"o":[[0,0],[-1.66,1.439],[-1.59,2.817],[0,0],[0,0],[0,0],[0,0]],"v":[[3.637,-31.53],[-8.73,-20.81],[-12.826,-15.801],[-15.277,-6.47],[-15.277,31.53],[15.277,9.515],[14.874,-26.362]]},"ix":2}},{"ty":"fl","bm":0,"hd":false,"mn":"ADBE Vector Graphic - Fill","nm":"Fill 1","c":{"a":0,"k":[0.5451,0.5451,0.5451],"ix":4},"r":1,"o":{"a":0,"k":100,"ix":5}},{"ty":"tr","a":{"a":0,"k":[0,0],"ix":1},"s":{"a":0,"k":[100,100],"ix":3},"sk":{"a":0,"k":0,"ix":4},"p":{"a":0,"k":[503.632,588.807],"ix":2},"r":{"a":0,"k":0,"ix":6},"sa":{"a":0,"k":0,"ix":5},"o":{"a":0,"k":100,"ix":7}}]},{"ty":"gr","bm":0,"hd":false,"mn":"ADBE Vector Group","nm":"Group 11","ix":10,"cix":2,"np":2,"it":[{"ty":"sh","bm":0,"hd":false,"mn":"ADBE Vector Shape - Group","nm":"Path 1","ix":1,"d":1,"ks":{"a":0,"k":{"c":true,"i":[[0,0],[0,0],[0,0],[0,0],[0,0],[0,0],[0,0]],"o":[[0,0],[0,0],[0,0],[0,0],[0,0],[0,0],[0,0]],"v":[[17.974,-23.852],[0,-23.598],[-17.974,-23.852],[-29.3,23.852],[-0.136,23.852],[0.136,23.852],[29.3,23.852]]},"ix":2}},{"ty":"fl","bm":0,"hd":false,"mn":"ADBE Vector Graphic - Fill","nm":"Fill 1","c":{"a":0,"k":[0.5451,0.5451,0.5451],"ix":4},"r":1,"o":{"a":0,"k":100,"ix":5}},{"ty":"tr","a":{"a":0,"k":[0,0],"ix":1},"s":{"a":0,"k":[100,100],"ix":3},"sk":{"a":0,"k":0,"ix":4},"p":{"a":0,"k":[553.828,611.832],"ix":2},"r":{"a":0,"k":0,"ix":6},"sa":{"a":0,"k":0,"ix":5},"o":{"a":0,"k":100,"ix":7}}]}],"ind":1},{"ty":4,"nm":"Layer 2/c[1-2] Outlines","sr":1,"st":0,"op":150.000006109625,"ip":0,"hd":false,"ddd":0,"bm":0,"hasMask":false,"ao":0,"ks":{"a":{"a":0,"k":[555,611,0],"ix":1},"s":{"a":1,"k":[{"o":{"x":0.167,"y":0.167},"i":{"x":0.833,"y":0.833},"s":[100,100,100],"t":15},{"o":{"x":0.167,"y":0.167},"i":{"x":0.833,"y":0.833},"s":[70,70,100],"t":30},{"s":[100,100,100],"t":45.0000018328876}],"ix":6},"sk":{"a":0,"k":0},"p":{"a":0,"k":[555,611,0],"ix":2},"r":{"a":0,"k":0,"ix":10},"sa":{"a":0,"k":0},"o":{"a":0,"k":100,"ix":11}},"ef":[],"shapes":[{"ty":"gr","bm":0,"hd":false,"mn":"ADBE Vector Group","nm":"Group 1","ix":1,"cix":2,"np":2,"it":[{"ty":"sh","bm":0,"hd":false,"mn":"ADBE Vector Shape - Group","nm":"Path 1","ix":1,"d":1,"ks":{"a":0,"k":{"c":true,"i":[[8.69,5.029],[0,-10.764],[-8.69,-5.029],[0,10.762]],"o":[[-8.69,5.029],[0,10.762],[8.69,-5.029],[0,-10.764]],"v":[[0.001,-25.182],[-14.542,0.001],[0.001,25.182],[14.542,0.001]]},"ix":2}},{"ty":"fl","bm":0,"hd":false,"mn":"ADBE Vector Graphic - Fill","nm":"Fill 1","c":{"a":0,"k":[0.9569,0.8667,0.0471],"ix":4},"r":1,"o":{"a":0,"k":100,"ix":5}},{"ty":"tr","a":{"a":0,"k":[0,0],"ix":1},"s":{"a":0,"k":[100,100],"ix":3},"sk":{"a":0,"k":0,"ix":4},"p":{"a":0,"k":[554.328,664.941],"ix":2},"r":{"a":0,"k":0,"ix":6},"sa":{"a":0,"k":0,"ix":5},"o":{"a":0,"k":100,"ix":7}}]},{"ty":"gr","bm":0,"hd":false,"mn":"ADBE Vector Group","nm":"Group 2","ix":2,"cix":2,"np":2,"it":[{"ty":"sh","bm":0,"hd":false,"mn":"ADBE Vector Shape - Group","nm":"Path 1","ix":1,"d":1,"ks":{"a":0,"k":{"c":true,"i":[[13.195,7.637],[0,-16.342],[-13.196,-7.637],[0,16.343]],"o":[[-13.196,7.637],[0,16.343],[13.195,-7.637],[0,-16.342]],"v":[[0,-38.238],[-22.08,0],[0,38.237],[22.08,0]]},"ix":2}},{"ty":"fl","bm":0,"hd":false,"mn":"ADBE Vector Graphic - Fill","nm":"Fill 1","c":{"a":0,"k":[0.9686,0.702,0.0431],"ix":4},"r":1,"o":{"a":0,"k":100,"ix":5}},{"ty":"tr","a":{"a":0,"k":[0,0],"ix":1},"s":{"a":0,"k":[100,100],"ix":3},"sk":{"a":0,"k":0,"ix":4},"p":{"a":0,"k":[554.328,671.135],"ix":2},"r":{"a":0,"k":0,"ix":6},"sa":{"a":0,"k":0,"ix":5},"o":{"a":0,"k":100,"ix":7}}]},{"ty":"gr","bm":0,"hd":false,"mn":"ADBE Vector Group","nm":"Group 3","ix":3,"cix":2,"np":2,"it":[{"ty":"sh","bm":0,"hd":false,"mn":"ADBE Vector Shape - Group","nm":"Path 1","ix":1,"d":1,"ks":{"a":0,"k":{"c":true,"i":[[20.2,11.69],[0,-25.017],[-20.201,-11.689],[0,25.018]],"o":[[-20.201,11.69],[0,25.018],[20.2,-11.689],[0,-25.017]],"v":[[0,-58.535],[-33.801,0],[0,58.535],[33.801,0]]},"ix":2}},{"ty":"fl","bm":0,"hd":false,"mn":"ADBE Vector Graphic - Fill","nm":"Fill 1","c":{"a":0,"k":[0.9569,0.5725,0.1922],"ix":4},"r":1,"o":{"a":0,"k":100,"ix":5}},{"ty":"tr","a":{"a":0,"k":[0,0],"ix":1},"s":{"a":0,"k":[100,100],"ix":3},"sk":{"a":0,"k":0,"ix":4},"p":{"a":0,"k":[554.328,683.06],"ix":2},"r":{"a":0,"k":0,"ix":6},"sa":{"a":0,"k":0,"ix":5},"o":{"a":0,"k":100,"ix":7}}]},{"ty":"gr","bm":0,"hd":false,"mn":"ADBE Vector Group","nm":"Group 4","ix":4,"cix":2,"np":2,"it":[{"ty":"sh","bm":0,"hd":false,"mn":"ADBE Vector Shape - Group","nm":"Path 1","ix":1,"d":1,"ks":{"a":0,"k":{"c":true,"i":[[0,14.947],[25.796,14.929],[0,-31.948],[-6.703,-12.251],[-5.093,-15.111],[-1.919,-15.124],[0,0],[0,0],[0,0],[0,0],[0,0],[0,0],[-5.479,15.48],[-7.08,12.949]],"o":[[0,-31.948],[-25.796,14.929],[0,14.955],[7.7,14.074],[4.84,14.358],[0,0],[0,0],[0,0],[0,0],[0,0],[0,0],[2.079,-16.384],[4.896,-13.833],[6.695,-12.246]],"v":[[43.164,-39.303],[0,-114.054],[-43.165,-39.303],[-32.648,1.957],[-13.297,45.785],[-3.021,90.05],[0.002,113.873],[0.002,114.054],[0.014,113.964],[0.025,114.054],[0.025,113.873],[3.055,89.997],[14.568,42.148],[32.658,1.937]]},"ix":2}},{"ty":"fl","bm":0,"hd":false,"mn":"ADBE Vector Graphic - Fill","nm":"Fill 1","c":{"a":0,"k":[0.9686,0.4157,0.1922],"ix":4},"r":1,"o":{"a":0,"k":100,"ix":5}},{"ty":"tr","a":{"a":0,"k":[0,0],"ix":1},"s":{"a":0,"k":[100,100],"ix":3},"sk":{"a":0,"k":0,"ix":4},"p":{"a":0,"k":[554.328,726.634],"ix":2},"r":{"a":0,"k":0,"ix":6},"sa":{"a":0,"k":0,"ix":5},"o":{"a":0,"k":100,"ix":7}}]}],"ind":2}]}]}